aaaaaaa_future_typing.pth
future_typing/__init__.py
future_typing/cli.py
future_typing/codec.py
future_typing/py.typed
future_typing/utils.py
future_typing-0.4.1.dist-info/LICENSE
future_typing-0.4.1.dist-info/METADATA
future_typing-0.4.1.dist-info/WHEEL
future_typing-0.4.1.dist-info/entry_points.txt
future_typing-0.4.1.dist-info/top_level.txt
future_typing-0.4.1.dist-info/zip-safe
future_typing-0.4.1.dist-info/RECORD
