Metadata-Version: 2.1
Name: future_typing
Version: 0.4.1
Summary: Use generic type hints and new union syntax `|` with python 3.6+
Home-page: https://github.com/PrettyWood/future-typing
Author: Eric Jolibois
Author-email: em.jolibois@gmail.com
License: MIT
Platform: UNKNOWN
Classifier: Development Status :: 3 - Alpha
Classifier: Intended Audience :: Developers
Classifier: Operating System :: OS Independent
Classifier: License :: OSI Approved :: MIT License
Classifier: Programming Language :: Python
Classifier: Programming Language :: Python :: 3
Classifier: Programming Language :: Python :: 3 :: Only
Classifier: Programming Language :: Python :: 3.6
Classifier: Programming Language :: Python :: 3.7
Classifier: Programming Language :: Python :: 3.8
Classifier: Programming Language :: Python :: 3.9
Classifier: Programming Language :: Python :: 3.10
Classifier: Typing :: Typed
Requires-Python: >=3.6
Provides-Extra: test
Provides-Extra: dev
